passagemath_environment-10.6.43.post1.data/scripts/sage
passagemath_environment-10.6.43.post1.data/scripts/sage-env
passagemath_environment-10.6.43.post1.data/scripts/sage-num-threads.py
passagemath_environment-10.6.43.post1.data/scripts/sage-python
passagemath_environment-10.6.43.post1.data/scripts/sage-venv-config
passagemath_environment-10.6.43.post1.data/scripts/sage-version.sh
sage/all__sagemath_environment.py
sage/env.py
sage/version.py
sage/features/__init__.py
sage/features/all.py
sage/features/bliss.py
sage/features/cddlib.py
sage/features/coxeter3.py
sage/features/csdp.py
sage/features/cython.py
sage/features/databases.py
sage/features/dot2tex.py
sage/features/dvipng.py
sage/features/ecl.py
sage/features/eclib.py
sage/features/ecm.py
sage/features/ffmpeg.py
sage/features/four_ti_2.py
sage/features/fricas.py
sage/features/frobby.py
sage/features/gap.py
sage/features/gfan.py
sage/features/giac.py
sage/features/graph_generators.py
sage/features/graphviz.py
sage/features/igraph.py
sage/features/imagemagick.py
sage/features/info.py
sage/features/interfaces.py
sage/features/internet.py
sage/features/jmol.py
sage/features/join_feature.py
sage/features/kenzo.py
sage/features/latex.py
sage/features/latte.py
sage/features/lrs.py
sage/features/macaulay2.py
sage/features/mcqd.py
sage/features/meataxe.py
sage/features/meson_editable.py
sage/features/mip_backends.py
sage/features/msolve.py
sage/features/nauty.py
sage/features/normaliz.py
sage/features/palp.py
sage/features/pandoc.py
sage/features/pari.py
sage/features/pdf2svg.py
sage/features/phitigra.py
sage/features/pkg_systems.py
sage/features/planarity.py
sage/features/polymake.py
sage/features/poppler.py
sage/features/qepcad.py
sage/features/rubiks.py
sage/features/sagemath.py
sage/features/sat.py
sage/features/singular.py
sage/features/sirocco.py
sage/features/sloane_database.py
sage/features/sphinx.py
sage/features/standard.py
sage/features/symengine_py.py
sage/features/sympow.py
sage/features/tachyon.py
passagemath_environment-10.6.43.post1.dist-info/METADATA
passagemath_environment-10.6.43.post1.dist-info/WHEEL
passagemath_environment-10.6.43.post1.dist-info/top_level.txt
passagemath_environment-10.6.43.post1.dist-info/RECORD
