Metadata-Version: 2.4
Name: passagemath-environment
Version: 10.6.43.post1
Summary: passagemath: System and software environment
Author-email: The Sage Developers <sage-support@googlegroups.com>
Maintainer: Matthias Köppe, passagemath contributors
License-Expression: GPL-2.0-or-later
Project-URL: release notes, https://github.com/passagemath/passagemath/releases
Project-URL: repo (upstream), https://github.com/sagemath/sage
Project-URL: repo, https://github.com/passagemath/passagemath
Project-URL: documentation, https://passagemath.org/docs/latest
Project-URL: homepage (upstream), https://www.sagemath.org
Project-URL: discourse, https://passagemath.discourse.group
Project-URL: tracker (upstream), https://github.com/sagemath/sage/issues
Project-URL: tracker, https://github.com/passagemath/passagemath/issues
Classifier: Development Status :: 6 - Mature
Classifier: Intended Audience :: Education
Classifier: Intended Audience :: Science/Research
Classifier: Operating System :: POSIX
Classifier: Operating System :: POSIX :: Linux
Classifier: Operating System :: MacOS :: MacOS X
Classifier: Operating System :: Microsoft :: Windows
Classifier: Programming Language :: Python :: 3 :: Only
Classifier: Programming Language :: Python :: 3.10
Classifier: Programming Language :: Python :: 3.11
Classifier: Programming Language :: Python :: 3.12
Classifier: Programming Language :: Python :: 3.13
Classifier: Programming Language :: Python :: 3.14
Classifier: Programming Language :: Python :: Implementation :: CPython
Classifier: Topic :: Scientific/Engineering :: Mathematics
Requires-Python: <3.15,>=3.10
Requires-Dist: packaging>=24.2
Requires-Dist: platformdirs
Provides-Extra: conf
Requires-Dist: passagemath-conf~=10.6.43.0; sys_platform != "win32" and extra == "conf"
Provides-Extra: docbuild
Requires-Dist: passagemath-docbuild~=10.6.43.0; extra == "docbuild"
Provides-Extra: sage
Requires-Dist: passagemath-standard~=10.6.43.0; extra == "sage"
Provides-Extra: cython
Requires-Dist: cython<3.3.0,>=3.0.8; extra == "cython"
Requires-Dist: cython<3.3.0,>=3.0.8; extra == "cython"
Provides-Extra: pytest
Requires-Dist: pytest; extra == "pytest"
Provides-Extra: rst2ipynb
Requires-Dist: rst2ipynb>=0.2.2; extra == "rst2ipynb"
Provides-Extra: tox
Requires-Dist: tox>=4.11; extra == "tox"
Provides-Extra: sws2rst
Requires-Dist: passagemath-sws2rst~=10.6.43.0; extra == "sws2rst"
